aime_detector_sdk/__init__.py
aime_detector_sdk/demo_app.py
aime_detector_sdk/detect_tracker.py
aime_detector_sdk/engines.py
aime_detector_sdk/types.py
aime_detector_sdk/utilities.py
aime_detector_sdk-0.1.5.post5.dist-info/LICENSE.txt
aime_detector_sdk-0.1.5.post5.dist-info/METADATA
aime_detector_sdk-0.1.5.post5.dist-info/WHEEL
aime_detector_sdk-0.1.5.post5.dist-info/top_level.txt
aime_detector_sdk-0.1.5.post5.dist-info/RECORD
