Metadata-Version: 2.1
Name: aime-detector-sdk
Version: 0.1.5.post5
Summary: Base module for human detection
Home-page: https://github.com/jarklee/aime_detector_sdk
Author: TrinhQuan
Author-email: quantv@aimesoft.com
License: UNKNOWN
Download-URL: https://github.com/jarklee/aime_detector_sdk/releases/download/0.1.5-5/aime_detector_sdk-0.1.5-post5.tar.gz
Platform: UNKNOWN
Classifier: Programming Language :: Python :: 3.6
Classifier: Programming Language :: Python :: 3.7
Classifier: License :: OSI Approved :: MIT License
Requires-Dist: opencv-python (==4.1.0.25)
